remotemath/__init__.py
remotemath/_version.py
remotemath/operations.py
remotemath/service.py
remotemath-17.3.0.dist-info/DESCRIPTION.rst
remotemath-17.3.0.dist-info/METADATA
remotemath-17.3.0.dist-info/RECORD
remotemath-17.3.0.dist-info/WHEEL
remotemath-17.3.0.dist-info/metadata.json
remotemath-17.3.0.dist-info/top_level.txt
twisted/plugins/remotemath.py
