Metadata-Version: 2.0
Name: remotemath
Version: 17.3.0
Summary: Math. Remote.
Home-page: UNKNOWN
Author: Moshe Zadka
Author-email: zadka.moshe@gmail.com
License: MIT
Platform: UNKNOWN
Requires-Dist: incremental
Requires-Dist: klein
